cc_net_prepro.py
doc_Gopher_statistics.py
doc_c4_statistics.py
doc_id_local.py
doc_id_local_python.py
doc_id_transform_base.py
doc_id_transform_python.py
doc_quality_local.py
doc_quality_local_python.py
doc_quality_transform.py
doc_quality_transform_python.py
doc_quality_utils.py
ededup_local.py
ededup_local_python.py
ededup_local_python_incremental.py
ededup_transform_base.py
ededup_transform_python.py
filter_local.py
filter_local_python.py
filter_test_support.py
filter_transform.py
filter_transform_python.py
html2parquet_local.py
html2parquet_local_python.py
html2parquet_transform.py
html2parquet_transform_python.py
lang_id_local.py
lang_id_local_python.py
lang_id_transform.py
lang_id_transform_python.py
lang_models.py
nlp.py
resize_local.py
resize_local_python.py
resize_transform.py
resize_transform_python.py
text_encoder_local.py
text_encoder_local_python.py
text_encoder_transform.py
text_encoder_transform_python.py
tokenization_local_long_doc_python.py
tokenization_local_python.py
tokenization_s3_long_doc_python.py
tokenization_transform.py
tokenization_transform_python.py
tokenization_utils.py
data_prep_toolkit_transforms_lang1-0.2.2.dist-info/METADATA
data_prep_toolkit_transforms_lang1-0.2.2.dist-info/WHEEL
data_prep_toolkit_transforms_lang1-0.2.2.dist-info/top_level.txt
data_prep_toolkit_transforms_lang1-0.2.2.dist-info/RECORD
