Metadata-Version: 2.1
Name: data_prep_toolkit_transforms_lang1
Version: 0.2.2
Summary: Data Preparation Toolkit Transforms
Author-email: Maroun Touma <touma@us.ibm.com>
License: Apache-2.0
Keywords: transforms,data preprocessing,data preparation,llm,generative,ai,fine-tuning,llmapps
Requires-Python: <3.12,>=3.10
Requires-Dist: data-prep-toolkit>=0.2.1
Requires-Dist: duckdb>=0.10.1
Requires-Dist: fasttext==0.9.2
Requires-Dist: langcodes==3.3.0
Requires-Dist: huggingface-hub<1.0.0,>=0.21.4
Requires-Dist: numpy==1.26.4
Requires-Dist: mmh3>=4.1.0
Requires-Dist: xxhash==3.4.1
Requires-Dist: tqdm==4.66.3
Requires-Dist: scipy==1.12.0
Requires-Dist: sentence-transformers>=3.0.1
Requires-Dist: trafilatura==1.12.0
Requires-Dist: transformers==4.38.2
